opensuse_distro_aliases/__init__.py
opensuse_distro_aliases/py.typed
opensuse_distro_aliases-0.2.3.dist-info/COPYING
opensuse_distro_aliases-0.2.3.dist-info/METADATA
opensuse_distro_aliases-0.2.3.dist-info/WHEEL
opensuse_distro_aliases-0.2.3.dist-info/RECORD
