Metadata-Version: 2.1
Name: opensuse-distro-aliases
Version: 0.2.3
Summary: Aliases for active openSUSE releases
License: MIT
Author: Dan Čermák
Author-email: dcermak@suse.com
Requires-Python: >=3.9,<4.0
Classifier: License :: OSI Approved :: MIT License
Classifier: Programming Language :: Python :: 3
Classifier: Programming Language :: Python :: 3.9
Classifier: Programming Language :: Python :: 3.10
Classifier: Programming Language :: Python :: 3.11
Classifier: Programming Language :: Python :: 3.12
Classifier: Programming Language :: Python :: 3.13
Requires-Dist: requests (>=2.25)
